go2_webrtc_driver/__init__.py
go2_webrtc_driver/constants.py
go2_webrtc_driver/encryption.py
go2_webrtc_driver/multicast_scanner.py
go2_webrtc_driver/unitree_auth.py
go2_webrtc_driver/util.py
go2_webrtc_driver/webrtc_audio.py
go2_webrtc_driver/webrtc_audiohub.py
go2_webrtc_driver/webrtc_datachannel.py
go2_webrtc_driver/webrtc_driver.py
go2_webrtc_driver/webrtc_video.py
go2_webrtc_driver/lidar/libvoxel.wasm
go2_webrtc_driver/lidar/lidar_decoder_libvoxel.py
go2_webrtc_driver/lidar/lidar_decoder_native.py
go2_webrtc_driver/lidar/lidar_decoder_unified.py
go2_webrtc_driver/msgs/error_handler.py
go2_webrtc_driver/msgs/future_resolver.py
go2_webrtc_driver/msgs/heartbeat.py
go2_webrtc_driver/msgs/pub_sub.py
go2_webrtc_driver/msgs/rtc_inner_req.py
go2_webrtc_driver/msgs/validation.py
go2_webrtc_connect-0.2.1.dist-info/METADATA
go2_webrtc_connect-0.2.1.dist-info/WHEEL
go2_webrtc_connect-0.2.1.dist-info/top_level.txt
go2_webrtc_connect-0.2.1.dist-info/RECORD
