Metadata-Version: 2.4
Name: go2-webrtc-connect
Version: 0.2.1
Summary: Connect to the Unitree Go2 with WebRTC
Author-email: legion1581 <legion1581@gmail.com>, phospho <contact@phospho.ai>
Requires-Python: >=3.8
Requires-Dist: aiortc>=1.9.0
Requires-Dist: pycryptodome
Requires-Dist: requests
Requires-Dist: wasmtime
Requires-Dist: flask-socketio
Requires-Dist: lz4
Requires-Dist: numpy
Requires-Dist: packaging
Provides-Extra: dev
Requires-Dist: ruff>=0.8.1; extra == "dev"
Requires-Dist: mypy>=1.13.0; extra == "dev"
Requires-Dist: types-requests>=2.32; extra == "dev"
Provides-Extra: audio
Requires-Dist: sounddevice; extra == "audio"
Requires-Dist: pyaudio; extra == "audio"
Requires-Dist: pydub; extra == "audio"
Provides-Extra: video
Requires-Dist: opencv-python-headless; extra == "video"
